CheeseAPI_APIDocumenter/__init__.py
CheeseAPI_APIDocumenter/command.py
CheeseAPI_APIDocumenter/documenter.py
cheeseapi_apidocumenter-0.0.1.dist-info/METADATA
cheeseapi_apidocumenter-0.0.1.dist-info/WHEEL
cheeseapi_apidocumenter-0.0.1.dist-info/entry_points.txt
cheeseapi_apidocumenter-0.0.1.dist-info/licenses/LICENSE
cheeseapi_apidocumenter-0.0.1.dist-info/RECORD
