Metadata-Version: 2.3
Name: CheeseAPI_APIDocumenter
Version: 0.0.1
Summary: 一款基于CheeseAPI的api接口文档管理器。
Project-URL: Source, https://github.com/CheeseUnknown/CheeseAPI_APIDocumenter
Author-email: Cheese Unknown <cheese@cheese.ren>
License-File: LICENSE
Keywords: API,CheeseAPI,Document,Documenter
Requires-Dist: cheeseapi==1.1.*
Requires-Dist: click
